LinuxServerStatsTelegramBot/DI.py
LinuxServerStatsTelegramBot/__init__.py
LinuxServerStatsTelegramBot/bot.py
LinuxServerStatsTelegramBot/cli.py
LinuxServerStatsTelegramBot/assets/794326550395748710.webp
LinuxServerStatsTelegramBot/assets/__init__.py
LinuxServerStatsTelegramBot/commmand/CleanMemory.py
LinuxServerStatsTelegramBot/commmand/Command.py
LinuxServerStatsTelegramBot/commmand/ConvertTextToImage.py
LinuxServerStatsTelegramBot/commmand/CpuStats.py
LinuxServerStatsTelegramBot/commmand/CronStats.py
LinuxServerStatsTelegramBot/commmand/DateAndLocation.py
LinuxServerStatsTelegramBot/commmand/DiskStats.py
LinuxServerStatsTelegramBot/commmand/DockerStats.py
LinuxServerStatsTelegramBot/commmand/MemoryStats.py
LinuxServerStatsTelegramBot/commmand/RebootApp.py
LinuxServerStatsTelegramBot/commmand/RebootContainer.py
LinuxServerStatsTelegramBot/commmand/SendProgrammerBeeSticker.py
LinuxServerStatsTelegramBot/commmand/ServersHealth.py
LinuxServerStatsTelegramBot/commmand/__init__.py
LinuxServerStatsTelegramBot/core/Invoker.py
LinuxServerStatsTelegramBot/core/__init__.py
LinuxServerStatsTelegramBot/sender/DebugSender.py
LinuxServerStatsTelegramBot/sender/Sender.py
LinuxServerStatsTelegramBot/sender/TelegramSender.py
LinuxServerStatsTelegramBot/sender/__init__.py
tests/__init__.py
tests/test_crontab_command.py
LinuxServerStatsTelegramBot-1.0.12.dist-info/METADATA
LinuxServerStatsTelegramBot-1.0.12.dist-info/WHEEL
LinuxServerStatsTelegramBot-1.0.12.dist-info/entry_points.txt
LinuxServerStatsTelegramBot-1.0.12.dist-info/top_level.txt
LinuxServerStatsTelegramBot-1.0.12.dist-info/RECORD
