Metadata-Version: 2.1
Name: LinuxServerStatsTelegramBot
Version: 1.0.12
Summary: Telegram bot manager to show linux server stats
Home-page: 
Author: Juares Vermelho Diaz
Author-email: j.vermelho@gmail.com
License: MIT
Requires-Dist: geocoder==1.38.1
Requires-Dist: gps==3.19
Requires-Dist: python-crontab==3.3.0
Requires-Dist: python-nmap==0.7.1
Requires-Dist: pytz==2025.2
Requires-Dist: ratelim==0.1.6
Requires-Dist: exceptiongroup==1.3.0; python_version < "3.11"
Requires-Dist: typing-extensions==4.14.1; python_version < "3.13"
Requires-Dist: croniter==6.0.0; python_version >= "2.6" and python_version not in "3.0, 3.1, 3.2, 3.3"
Requires-Dist: future==1.0.0; python_version >= "2.6" and python_version not in "3.0, 3.1, 3.2, 3.3"
Requires-Dist: python-dateutil==2.9.0.post0; python_version >= "2.7" and python_version not in "3.0, 3.1, 3.2, 3.3"
Requires-Dist: six==1.17.0; python_version >= "2.7" and python_version not in "3.0, 3.1, 3.2, 3.3"
Requires-Dist: idna==3.10; python_version >= "3.6"
Requires-Dist: certifi==2025.8.3; python_version >= "3.7"
Requires-Dist: charset-normalizer==3.4.3; python_version >= "3.7"
Requires-Dist: click==8.1.8; python_version >= "3.7"
Requires-Dist: sniffio==1.3.1; python_version >= "3.7"
Requires-Dist: decorator==5.2.1; python_version >= "3.8"
Requires-Dist: h11==0.16.0; python_version >= "3.8"
Requires-Dist: httpcore==1.0.9; python_version >= "3.8"
Requires-Dist: httpx==0.28.1; python_version >= "3.8"
Requires-Dist: requests==2.32.4; python_version >= "3.8"
Requires-Dist: anyio==4.10.0; python_version >= "3.9"
Requires-Dist: pillow==11.3.0; python_version >= "3.9"
Requires-Dist: python-telegram-bot==22.3; python_version >= "3.9"
Requires-Dist: urllib3==2.5.0; python_version >= "3.9"
